conp_pipeline/__init__.py
conp_pipeline/conp_pipeline.py
conp_pipeline-0.2.dist-info/METADATA
conp_pipeline-0.2.dist-info/RECORD
conp_pipeline-0.2.dist-info/WHEEL
conp_pipeline-0.2.dist-info/entry_points.txt
conp_pipeline-0.2.dist-info/top_level.txt
